ghtop/__init__.py
ghtop/_nbdev.py
ghtop/ghtop.py
ghtop-0.0.8.dist-info/METADATA
ghtop-0.0.8.dist-info/WHEEL
ghtop-0.0.8.dist-info/entry_points.txt
ghtop-0.0.8.dist-info/top_level.txt
ghtop-0.0.8.dist-info/RECORD
