Metadata-Version: 2.1
Name: ghtop
Version: 0.0.8
Summary: See what is happening on GitHub in real time
Home-page: https://github.com/fastai/ghtop/tree/master/
Author: natfriedman
Author-email: j@fast.ai
License: MIT
Keywords: python
Platform: UNKNOWN
Classifier: Development Status :: 3 - Alpha
Classifier: Intended Audience :: Developers
Classifier: License :: OSI Approved :: MIT License
Classifier: Natural Language :: English
Classifier: Programming Language :: Python :: 3.6
Classifier: Programming Language :: Python :: 3.7
Classifier: Programming Language :: Python :: 3.8
Requires-Python: >=3.6
Requires-Dist: emoji
Requires-Dist: enlighten
Requires-Dist: py-dashing
Requires-Dist: fastcore
Requires-Dist: ghapi (>0.1.13)
